djangocms_currentuser_field/__init__.py
djangocms_currentuser_field/cms_plugins.py
djangocms_currentuser_field/models.py
djangocms_currentuser_field/__pycache__/__init__.cpython-38.pyc
djangocms_currentuser_field/__pycache__/cms_plugins.cpython-38.pyc
djangocms_currentuser_field/__pycache__/models.cpython-38.pyc
djangocms_currentuser_field/migrations/0001_initial.py
djangocms_currentuser_field/migrations/__init__.py
djangocms_currentuser_field/migrations/__pycache__/0001_initial.cpython-38.pyc
djangocms_currentuser_field/migrations/__pycache__/__init__.cpython-38.pyc
djangocms_currentuser_field-0.6.dist-info/LICENSE
djangocms_currentuser_field-0.6.dist-info/METADATA
djangocms_currentuser_field-0.6.dist-info/WHEEL
djangocms_currentuser_field-0.6.dist-info/top_level.txt
djangocms_currentuser_field-0.6.dist-info/RECORD
